LICENSE
MANIFEST.in
README.rst
setup.cfg
setup.py
eqdes/__about__.py
eqdes/__init__.py
eqdes/dba.py
eqdes/dbd.py
eqdes/dbd_tools.py
eqdes/design_spectra.py
eqdes/fns.py
eqdes/models.py
eqdes/moment_equilibrium.py
eqdes/nonlinear_foundation.py
eqdes/section_designer.py
eqdes.egg-info/PKG-INFO
eqdes.egg-info/SOURCES.txt
eqdes.egg-info/dependency_links.txt
eqdes.egg-info/not-zip-safe
eqdes.egg-info/requires.txt
eqdes.egg-info/top_level.txt
eqdes/extensions/__init__.py
eqdes/extensions/exceptions.py