Metadata-Version: 2.1
Name: eqdes
Version: 0.3.3
Summary: This package contains solvers for structural design of buildings for earthquakes
Home-page: UNKNOWN
Author: Maxim Millen
Author-email: mmi46@uclive.ac.nz
License: MIT
Platform: UNKNOWN
Classifier: Development Status :: 3 - Alpha
Classifier: Intended Audience :: Science/Research
Classifier: Topic :: Scientific/Engineering
Classifier: License :: OSI Approved :: MIT License
Classifier: Programming Language :: Python :: 3
Requires-Python: >=3
Provides-Extra: test
